.DS_Store
gmlutil_data_extraction/config.py
gmlutil_data_extraction/data_extraction.py
gmlutil_data_extraction-2.1.0.dist-info/METADATA
gmlutil_data_extraction-2.1.0.dist-info/WHEEL
gmlutil_data_extraction-2.1.0.dist-info/top_level.txt
gmlutil_data_extraction-2.1.0.dist-info/RECORD
