Metadata-Version: 2.1
Name: gmlutil-data-extraction
Version: 2.1.0
Summary: General Machine Learning Utility Package for Data Extraction
Home-page: https://git.ejgallo.com/prophet-data-science/central-data-science-library/gmlutil-data-extraction.git
Author: Phillip Kim
Author-email: phillip.kim@ejgallo.com
License: BSD 2-clause
Classifier: Development Status :: 5 - Production/Stable
Classifier: Framework :: IPython
Classifier: Intended Audience :: Developers
Classifier: License :: OSI Approved :: BSD License
Classifier: Operating System :: MacOS
Classifier: Operating System :: Microsoft :: Windows :: Windows XP
Classifier: Operating System :: POSIX :: Linux
Classifier: Programming Language :: Python :: 3.9
Classifier: Programming Language :: Python :: 3.10
Classifier: Programming Language :: Python :: 3.11
Classifier: Programming Language :: Python :: 3.12
Requires-Dist: setuptools (==69.0.0)
Requires-Dist: botocore (==1.35.0)
Requires-Dist: aiobotocore (==2.14.0)
Requires-Dist: boto3 (==1.35.0)
Requires-Dist: awscli (==1.34.0)
Requires-Dist: numpy (==1.26.4)
Requires-Dist: pandas (<=2.2.2,>2.1.0)
Requires-Dist: astropy (>=6.0.0)
Requires-Dist: fuzzywuzzy (>=0.18.0)
Requires-Dist: geopandas (>=0.10.2)
Requires-Dist: hana-ml
Requires-Dist: numba (>=0.60.0)
Requires-Dist: oracledb (>=1.4.2)
Requires-Dist: psycopg2-binary (>=2.9.1)
Requires-Dist: pyarrow (>=17.0.0)
Requires-Dist: pymssql (>=2.2.1)
Requires-Dist: python-levenshtein-wheels (>=0.13.1)
Requires-Dist: pytrends (>=4.7.3)
Requires-Dist: redshift-connector (>=2.1.5)
Requires-Dist: sagemaker (>=2.229.0)
Requires-Dist: sagemaker-data-insights (>=0.4.0)
Requires-Dist: sqlalchemy-redshift (>=0.8.6)
